Workbook

Sheet Instruções
A1: TradeMiles — Inventário de funções (venda de código)
A3: Como usar
A4: 1. Abra a aba 'Funções'.
A5: 2. Na coluna E (Interesse?), escolha Sim ou Não para cada item.
A6: 3. Use a coluna F (Observações do interessado) para anotar o que importa.
A7: 4. A aba 'Resumo' conta automaticamente quantos Sim/Não/em branco.
A8: 5. Filtre por Módulo ou Interesse no Excel (Dados → Filtro).
A10: Contexto: inventário baseado no código atual do TradeMiles (dashboard, APIs, VIP, afiliados, extensão LATAM).
A11: Não inclui itens de menu sem implementação real (ex.: Automação sem página).
A13: Sugestão de uso comercial: envie esta planilha ao comprador e peça para marcar o que quer manter/customizar.

Sheet Funções
A1: # | B1: Módulo | C1: Função | D1: Descrição | E1: Interesse? | F1: Observações do interessado | G1: Complexidade no código
A2: 1 | B2: Autenticação e acesso | C2: Login staff/admin | D2: Login em /login com cookie de sessão e proteção do dashboard | G2: Alta
A3: 2 | B3: Autenticação e acesso | C3: Sessão e roles | D3: Sessão com roles admin/staff e refresh de sessão | G3: Alta
A4: 3 | B4: Autenticação e acesso | C4: Logout | D4: Encerramento de sessão pelo menu | G4: Baixa
A5: 4 | B5: Autenticação e acesso | C5: Configurações (admin) | D5: Comissões, bônus e alertas de e-mail (protegido) | G5: Alta
A6: 5 | B6: Página inicial e equipe | C6: Página inicial | D6: Agenda do dia + presença online da equipe | G6: Média
A7: 6 | B7: Página inicial e equipe | C7: Presence ping | D7: Heartbeat de presença dos usuários logados | G7: Baixa
A8: 7 | B8: Página inicial e equipe | C8: Agenda (turnos/faltas) | D8: CRUD de eventos SHIFT/ABSENCE com cores por membro | G8: Média
A9: 8 | B9: Página inicial e equipe | C9: Avisos | D9: Quadro de avisos por grupo/usuário (pendente/resolvido) | G9: Média
A10: 9 | B10: Página inicial e equipe | C10: Anotações | D10: Notas internas da equipe | G10: Baixa
A11: 10 | B11: Cedentes | C11: Cadastrar cedente | D11: Formulário interno de novo cedente | G11: Alta
A12: 11 | B12: Cedentes | C12: Importar cedentes | D12: Importação em lote de cedentes | G12: Alta
A13: 12 | B13: Cedentes | C13: Cedentes pendentes | D13: Fila de aprovação/revisão de cadastros | G13: Alta
... A103: 102 | B103: Infra / Stack | C103: Credenciais sensíveis | D103: Reveal controlado, cards, exclusão com PDF | G103: Alta

Sheet Resumo
A1: Resumo de interesse
A3: Total de funções | B3: =COUNTA(Funções!C2:C103)
A4: Com interesse (Sim) | B4: =COUNTIF(Funções!E2:E103,"Sim")
A5: Sem interesse (Não) | B5: =COUNTIF(Funções!E2:E103,"Não")
A6: Em branco | B6: =COUNTBLANK(Funções!E2:E103)
A8: Por módulo (marque Interesse na aba Funções; este bloco é referência)
A9: Módulo | B9: Qtd funções | C9: Sim | D9: Não
A10: Autenticação e acesso | B10: =COUNTIF(Funções!B:B,A10) | C10: =COUNTIFS(Funções!B:B,A10,Funções!E:E,"Sim") | D10: =COUNTIFS(Funções!B:B,A10,Funções!E:E,"Não")
A11: Página inicial e equipe | B11: =COUNTIF(Funções!B:B,A11) | C11: =COUNTIFS(Funções!B:B,A11,Funções!E:E,"Sim") | D11: =COUNTIFS(Funções!B:B,A11,Funções!E:E,"Não")
A12: Cedentes | B12: =COUNTIF(Funções!B:B,A12) | C12: =COUNTIFS(Funções!B:B,A12,Funções!E:E,"Sim") | D12: =COUNTIFS(Funções!B:B,A12,Funções!E:E,"Não")
A13: Funcionários | B13: =COUNTIF(Funções!B:B,A13) | C13: =COUNTIFS(Funções!B:B,A13,Funções!E:E,"Sim") | D13: =COUNTIFS(Funções!B:B,A13,Funções!E:E,"Não")
A14: Clientes | B14: =COUNTIF(Funções!B:B,A14) | C14: =COUNTIFS(Funções!B:B,A14,Funções!E:E,"Sim") | D14: =COUNTIFS(Funções!B:B,A14,Funções!E:E,"Não")
A15: Afiliados (admin) | B15: =COUNTIF(Funções!B:B,A15) | C15: =COUNTIFS(Funções!B:B,A15,Funções!E:E,"Sim") | D15: =COUNTIFS(Funções!B:B,A15,Funções!E:E,"Não")
A16: Pendências | B16: =COUNTIF(Funções!B:B,A16) | C16: =COUNTIFS(Funções!B:B,A16,Funções!E:E,"Sim") | D16: =COUNTIFS(Funções!B:B,A16,Funções!E:E,"Não")
A17: Pontos | B17: =COUNTIF(Funções!B:B,A17) | C17: =COUNTIFS(Funções!B:B,A17,Funções!E:E,"Sim") | D17: =COUNTIFS(Funções!B:B,A17,Funções!E:E,"Não")
A18: Clubes | B18: =COUNTIF(Funções!B:B,A18) | C18: =COUNTIFS(Funções!B:B,A18,Funções!E:E,"Sim") | D18: =COUNTIFS(Funções!B:B,A18,Funções!E:E,"Não")
A19: Compras | B19: =COUNTIF(Funções!B:B,A19) | C19: =COUNTIFS(Funções!B:B,A19,Funções!E:E,"Sim") | D19: =COUNTIFS(Funções!B:B,A19,Funções!E:E,"Não")
A20: Vendas | B20: =COUNTIF(Funções!B:B,A20) | C20: =COUNTIFS(Funções!B:B,A20,Funções!E:E,"Sim") | D20: =COUNTIFS(Funções!B:B,A20,Funções!E:E,"Não")
A21: Check Localizador | B21: =COUNTIF(Funções!B:B,A21) | C21: =COUNTIFS(Funções!B:B,A21,Funções!E:E,"Sim") | D21: =COUNTIFS(Funções!B:B,A21,Funções!E:E,"Não")
... A38: Infra / Stack | B38: =COUNTIF(Funções!B:B,A38) | C38: =COUNTIFS(Funções!B:B,A38,Funções!E:E,"Sim") | D38: =COUNTIFS(Funções!B:B,A38,Funções!E:E,"Não")
